{
  "_format": "hh-sol-cache-2",
  "files": {
    "/Users/kimberleycheung/CiviXchain/civicxchain-platform/contracts/contracts/CivicXChainGovernance.sol": {
      "lastModificationDate": 1753387946039,
      "contentHash": "74bc7ab552fe9c1718e0081a32a7c57e",
      "sourceName": "contracts/CivicXChainGovernance.sol",
      "solcConfig": {
        "version": "0.8.28",
        "settings": {
          "optimizer": {
            "enabled": true,
            "runs": 200
          },
          "viaIR": true,
          "evmVersion": "paris",
          "outputSelection": {
            "*": {
              "*": [
                "abi",
                "evm.bytecode",
                "evm.deployedBytecode",
                "evm.methodIdentifiers",
                "metadata"
              ],
              "": [
                "ast"
              ]
            }
          }
        }
      },
      "imports": [
        "@openzeppelin/contracts/token/ERC20/ERC20.sol",
        "@openzeppelin/contracts/access/Ownable.sol",
        "@openzeppelin/contracts/security/ReentrancyGuard.sol",
        "@chainlink/contracts/src/v0.8/interfaces/AggregatorV3Interface.sol"
      ],
      "versionPragmas": [
        "^0.8.19"
      ],
      "artifacts": [
        "CivicXChainGovernance"
      ]
    },
    "/Users/kimberleycheung/CiviXchain/civicxchain-platform/contracts/node_modules/@openzeppelin/contracts/access/Ownable.sol": {
      "lastModificationDate": 1753387626361,
      "contentHash": "5a20b2cad87ddb61c7a3a6af21289e28",
      "sourceName": "@openzeppelin/contracts/access/Ownable.sol",
      "solcConfig": {
        "version": "0.8.28",
        "settings": {
          "optimizer": {
            "enabled": true,
            "runs": 200
          },
          "viaIR": true,
          "evmVersion": "paris",
          "outputSelection": {
            "*": {
              "*": [
                "abi",
                "evm.bytecode",
                "evm.deployedBytecode",
                "evm.methodIdentifiers",
                "metadata"
              ],
              "": [
                "ast"
              ]
            }
          }
        }
      },
      "imports": [
        "../utils/Context.sol"
      ],
      "versionPragmas": [
        "^0.8.0"
      ],
      "artifacts": [
        "Ownable"
      ]
    },
    "/Users/kimberleycheung/CiviXchain/civicxchain-platform/contracts/node_modules/@openzeppelin/contracts/token/ERC20/ERC20.sol": {
      "lastModificationDate": 1753387626184,
      "contentHash": "3ae5166c6827a9cf1a7a462d1632b464",
      "sourceName": "@openzeppelin/contracts/token/ERC20/ERC20.sol",
      "solcConfig": {
        "version": "0.8.28",
        "settings": {
          "optimizer": {
            "enabled": true,
            "runs": 200
          },
          "viaIR": true,
          "evmVersion": "paris",
          "outputSelection": {
            "*": {
              "*": [
                "abi",
                "evm.bytecode",
                "evm.deployedBytecode",
                "evm.methodIdentifiers",
                "metadata"
              ],
              "": [
                "ast"
              ]
            }
          }
        }
      },
      "imports": [
        "./IERC20.sol",
        "./extensions/IERC20Metadata.sol",
        "../../utils/Context.sol"
      ],
      "versionPragmas": [
        "^0.8.0"
      ],
      "artifacts": [
        "ERC20"
      ]
    },
    "/Users/kimberleycheung/CiviXchain/civicxchain-platform/contracts/node_modules/@openzeppelin/contracts/security/ReentrancyGuard.sol": {
      "lastModificationDate": 1753387626367,
      "contentHash": "1535f8c0c68463f8c1b5239f7584e71f",
      "sourceName": "@openzeppelin/contracts/security/ReentrancyGuard.sol",
      "solcConfig": {
        "version": "0.8.28",
        "settings": {
          "optimizer": {
            "enabled": true,
            "runs": 200
          },
          "viaIR": true,
          "evmVersion": "paris",
          "outputSelection": {
            "*": {
              "*": [
                "abi",
                "evm.bytecode",
                "evm.deployedBytecode",
                "evm.methodIdentifiers",
                "metadata"
              ],
              "": [
                "ast"
              ]
            }
          }
        }
      },
      "imports": [],
      "versionPragmas": [
        "^0.8.0"
      ],
      "artifacts": [
        "ReentrancyGuard"
      ]
    },
    "/Users/kimberleycheung/CiviXchain/civicxchain-platform/contracts/node_modules/@chainlink/contracts/src/v0.8/interfaces/AggregatorV3Interface.sol": {
      "lastModificationDate": 1753387626411,
      "contentHash": "d9654a0fc044a31d4106ee6bca772add",
      "sourceName": "@chainlink/contracts/src/v0.8/interfaces/AggregatorV3Interface.sol",
      "solcConfig": {
        "version": "0.8.28",
        "settings": {
          "optimizer": {
            "enabled": true,
            "runs": 200
          },
          "viaIR": true,
          "evmVersion": "paris",
          "outputSelection": {
            "*": {
              "*": [
                "abi",
                "evm.bytecode",
                "evm.deployedBytecode",
                "evm.methodIdentifiers",
                "metadata"
              ],
              "": [
                "ast"
              ]
            }
          }
        }
      },
      "imports": [],
      "versionPragmas": [
        "^0.8.0"
      ],
      "artifacts": [
        "AggregatorV3Interface"
      ]
    },
    "/Users/kimberleycheung/CiviXchain/civicxchain-platform/contracts/node_modules/@openzeppelin/contracts/utils/Context.sol": {
      "lastModificationDate": 1753387626123,
      "contentHash": "f07feb4a44b1a4872370da5aa70e8e46",
      "sourceName": "@openzeppelin/contracts/utils/Context.sol",
      "solcConfig": {
        "version": "0.8.28",
        "settings": {
          "optimizer": {
            "enabled": true,
            "runs": 200
          },
          "viaIR": true,
          "evmVersion": "paris",
          "outputSelection": {
            "*": {
              "*": [
                "abi",
                "evm.bytecode",
                "evm.deployedBytecode",
                "evm.methodIdentifiers",
                "metadata"
              ],
              "": [
                "ast"
              ]
            }
          }
        }
      },
      "imports": [],
      "versionPragmas": [
        "^0.8.0"
      ],
      "artifacts": [
        "Context"
      ]
    },
    "/Users/kimberleycheung/CiviXchain/civicxchain-platform/contracts/node_modules/@openzeppelin/contracts/token/ERC20/IERC20.sol": {
      "lastModificationDate": 1753387626248,
      "contentHash": "df36f7051335cd1e748b1b6463b7fdd3",
      "sourceName": "@openzeppelin/contracts/token/ERC20/IERC20.sol",
      "solcConfig": {
        "version": "0.8.28",
        "settings": {
          "optimizer": {
            "enabled": true,
            "runs": 200
          },
          "viaIR": true,
          "evmVersion": "paris",
          "outputSelection": {
            "*": {
              "*": [
                "abi",
                "evm.bytecode",
                "evm.deployedBytecode",
                "evm.methodIdentifiers",
                "metadata"
              ],
              "": [
                "ast"
              ]
            }
          }
        }
      },
      "imports": [],
      "versionPragmas": [
        "^0.8.0"
      ],
      "artifacts": [
        "IERC20"
      ]
    },
    "/Users/kimberleycheung/CiviXchain/civicxchain-platform/contracts/node_modules/@openzeppelin/contracts/token/ERC20/extensions/IERC20Metadata.sol": {
      "lastModificationDate": 1753387626249,
      "contentHash": "909ab67fc5c25033fe6cd364f8c056f9",
      "sourceName": "@openzeppelin/contracts/token/ERC20/extensions/IERC20Metadata.sol",
      "solcConfig": {
        "version": "0.8.28",
        "settings": {
          "optimizer": {
            "enabled": true,
            "runs": 200
          },
          "viaIR": true,
          "evmVersion": "paris",
          "outputSelection": {
            "*": {
              "*": [
                "abi",
                "evm.bytecode",
                "evm.deployedBytecode",
                "evm.methodIdentifiers",
                "metadata"
              ],
              "": [
                "ast"
              ]
            }
          }
        }
      },
      "imports": [
        "../IERC20.sol"
      ],
      "versionPragmas": [
        "^0.8.0"
      ],
      "artifacts": [
        "IERC20Metadata"
      ]
    },
    "/Users/kimberleycheung/CiviXchain/civicxchain-platform/contracts/contracts/EnvironmentalDataOracle.sol": {
      "lastModificationDate": 1752618327946,
      "contentHash": "1330cc3ce108354a9c134c0ace5ac977",
      "sourceName": "contracts/EnvironmentalDataOracle.sol",
      "solcConfig": {
        "version": "0.8.28",
        "settings": {
          "optimizer": {
            "enabled": true,
            "runs": 200
          },
          "viaIR": true,
          "evmVersion": "paris",
          "outputSelection": {
            "*": {
              "*": [
                "abi",
                "evm.bytecode",
                "evm.deployedBytecode",
                "evm.methodIdentifiers",
                "metadata"
              ],
              "": [
                "ast"
              ]
            }
          }
        }
      },
      "imports": [],
      "versionPragmas": [
        "^0.8.19"
      ],
      "artifacts": [
        "EnvironmentalDataOracle"
      ]
    },
    "/Users/kimberleycheung/CiviXchain/civicxchain-platform/contracts/contracts/RealEnvironmentalOracle.sol": {
      "lastModificationDate": 1753581895865,
      "contentHash": "99181dec03a4e0bda6f5566b4fc6a2a0",
      "sourceName": "contracts/RealEnvironmentalOracle.sol",
      "solcConfig": {
        "version": "0.8.28",
        "settings": {
          "optimizer": {
            "enabled": true,
            "runs": 200
          },
          "viaIR": true,
          "evmVersion": "paris",
          "outputSelection": {
            "*": {
              "*": [
                "abi",
                "evm.bytecode",
                "evm.deployedBytecode",
                "evm.methodIdentifiers",
                "metadata"
              ],
              "": [
                "ast"
              ]
            }
          }
        }
      },
      "imports": [
        "@chainlink/contracts/src/v0.8/interfaces/AggregatorV3Interface.sol"
      ],
      "versionPragmas": [
        "^0.8.19"
      ],
      "artifacts": [
        "RealEnvironmentalOracle"
      ]
    },
    "/Users/kimberleycheung/CiviXchain/civicxchain-platform/contracts/contracts/ChainlinkEnvironmentalOracle.sol": {
      "lastModificationDate": 1753582164765,
      "contentHash": "f95cee155f60d6c1cc83ed0a8149a0bf",
      "sourceName": "contracts/ChainlinkEnvironmentalOracle.sol",
      "solcConfig": {
        "version": "0.8.28",
        "settings": {
          "optimizer": {
            "enabled": true,
            "runs": 200
          },
          "viaIR": true,
          "evmVersion": "paris",
          "outputSelection": {
            "*": {
              "*": [
                "abi",
                "evm.bytecode",
                "evm.deployedBytecode",
                "evm.methodIdentifiers",
                "metadata"
              ],
              "": [
                "ast"
              ]
            }
          }
        }
      },
      "imports": [
        "@chainlink/contracts/src/v0.8/interfaces/AggregatorV3Interface.sol",
        "@chainlink/contracts/src/v0.8/ChainlinkClient.sol",
        "@chainlink/contracts/src/v0.8/ConfirmedOwner.sol"
      ],
      "versionPragmas": [
        "^0.8.19"
      ],
      "artifacts": [
        "ChainlinkEnvironmentalOracle"
      ]
    },
    "/Users/kimberleycheung/CiviXchain/civicxchain-platform/contracts/node_modules/@chainlink/contracts/src/v0.8/ConfirmedOwner.sol": {
      "lastModificationDate": 1753387626452,
      "contentHash": "16d64572b0310127fc8a771e63be6d20",
      "sourceName": "@chainlink/contracts/src/v0.8/ConfirmedOwner.sol",
      "solcConfig": {
        "version": "0.8.28",
        "settings": {
          "optimizer": {
            "enabled": true,
            "runs": 200
          },
          "viaIR": true,
          "evmVersion": "paris",
          "outputSelection": {
            "*": {
              "*": [
                "abi",
                "evm.bytecode",
                "evm.deployedBytecode",
                "evm.methodIdentifiers",
                "metadata"
              ],
              "": [
                "ast"
              ]
            }
          }
        }
      },
      "imports": [
        "./ConfirmedOwnerWithProposal.sol"
      ],
      "versionPragmas": [
        "^0.8.0"
      ],
      "artifacts": [
        "ConfirmedOwner"
      ]
    },
    "/Users/kimberleycheung/CiviXchain/civicxchain-platform/contracts/node_modules/@chainlink/contracts/src/v0.8/ChainlinkClient.sol": {
      "lastModificationDate": 1753387626449,
      "contentHash": "6af479cbde42f1a7225c9cebc6e32239",
      "sourceName": "@chainlink/contracts/src/v0.8/ChainlinkClient.sol",
      "solcConfig": {
        "version": "0.8.28",
        "settings": {
          "optimizer": {
            "enabled": true,
            "runs": 200
          },
          "viaIR": true,
          "evmVersion": "paris",
          "outputSelection": {
            "*": {
              "*": [
                "abi",
                "evm.bytecode",
                "evm.deployedBytecode",
                "evm.methodIdentifiers",
                "metadata"
              ],
              "": [
                "ast"
              ]
            }
          }
        }
      },
      "imports": [
        "./Chainlink.sol",
        "./interfaces/ENSInterface.sol",
        "./interfaces/LinkTokenInterface.sol",
        "./interfaces/ChainlinkRequestInterface.sol",
        "./interfaces/OperatorInterface.sol",
        "./interfaces/PointerInterface.sol",
        "./vendor/ENSResolver.sol"
      ],
      "versionPragmas": [
        "^0.8.0"
      ],
      "artifacts": [
        "ChainlinkClient"
      ]
    },
    "/Users/kimberleycheung/CiviXchain/civicxchain-platform/contracts/node_modules/@chainlink/contracts/src/v0.8/ConfirmedOwnerWithProposal.sol": {
      "lastModificationDate": 1753387626458,
      "contentHash": "8b1c5f02622cd87472493bda6595d1be",
      "sourceName": "@chainlink/contracts/src/v0.8/ConfirmedOwnerWithProposal.sol",
      "solcConfig": {
        "version": "0.8.28",
        "settings": {
          "optimizer": {
            "enabled": true,
            "runs": 200
          },
          "viaIR": true,
          "evmVersion": "paris",
          "outputSelection": {
            "*": {
              "*": [
                "abi",
                "evm.bytecode",
                "evm.deployedBytecode",
                "evm.methodIdentifiers",
                "metadata"
              ],
              "": [
                "ast"
              ]
            }
          }
        }
      },
      "imports": [
        "./interfaces/OwnableInterface.sol"
      ],
      "versionPragmas": [
        "^0.8.0"
      ],
      "artifacts": [
        "ConfirmedOwnerWithProposal"
      ]
    },
    "/Users/kimberleycheung/CiviXchain/civicxchain-platform/contracts/node_modules/@chainlink/contracts/src/v0.8/interfaces/OwnableInterface.sol": {
      "lastModificationDate": 1753387626538,
      "contentHash": "2e814c8a9f77897f6995436d97c23d99",
      "sourceName": "@chainlink/contracts/src/v0.8/interfaces/OwnableInterface.sol",
      "solcConfig": {
        "version": "0.8.28",
        "settings": {
          "optimizer": {
            "enabled": true,
            "runs": 200
          },
          "viaIR": true,
          "evmVersion": "paris",
          "outputSelection": {
            "*": {
              "*": [
                "abi",
                "evm.bytecode",
                "evm.deployedBytecode",
                "evm.methodIdentifiers",
                "metadata"
              ],
              "": [
                "ast"
              ]
            }
          }
        }
      },
      "imports": [],
      "versionPragmas": [
        "^0.8.0"
      ],
      "artifacts": [
        "OwnableInterface"
      ]
    },
    "/Users/kimberleycheung/CiviXchain/civicxchain-platform/contracts/node_modules/@chainlink/contracts/src/v0.8/interfaces/ChainlinkRequestInterface.sol": {
      "lastModificationDate": 1753387626450,
      "contentHash": "14407a6ead15cff8a0e0a7f8037c68f5",
      "sourceName": "@chainlink/contracts/src/v0.8/interfaces/ChainlinkRequestInterface.sol",
      "solcConfig": {
        "version": "0.8.28",
        "settings": {
          "optimizer": {
            "enabled": true,
            "runs": 200
          },
          "viaIR": true,
          "evmVersion": "paris",
          "outputSelection": {
            "*": {
              "*": [
                "abi",
                "evm.bytecode",
                "evm.deployedBytecode",
                "evm.methodIdentifiers",
                "metadata"
              ],
              "": [
                "ast"
              ]
            }
          }
        }
      },
      "imports": [],
      "versionPragmas": [
        "^0.8.0"
      ],
      "artifacts": [
        "ChainlinkRequestInterface"
      ]
    },
    "/Users/kimberleycheung/CiviXchain/civicxchain-platform/contracts/node_modules/@chainlink/contracts/src/v0.8/Chainlink.sol": {
      "lastModificationDate": 1753387626447,
      "contentHash": "9dc050539cdf1579d5650d41d0df9ec2",
      "sourceName": "@chainlink/contracts/src/v0.8/Chainlink.sol",
      "solcConfig": {
        "version": "0.8.28",
        "settings": {
          "optimizer": {
            "enabled": true,
            "runs": 200
          },
          "viaIR": true,
          "evmVersion": "paris",
          "outputSelection": {
            "*": {
              "*": [
                "abi",
                "evm.bytecode",
                "evm.deployedBytecode",
                "evm.methodIdentifiers",
                "metadata"
              ],
              "": [
                "ast"
              ]
            }
          }
        }
      },
      "imports": [
        "./vendor/CBORChainlink.sol",
        "./vendor/BufferChainlink.sol"
      ],
      "versionPragmas": [
        "^0.8.0"
      ],
      "artifacts": [
        "Chainlink"
      ]
    },
    "/Users/kimberleycheung/CiviXchain/civicxchain-platform/contracts/node_modules/@chainlink/contracts/src/v0.8/interfaces/LinkTokenInterface.sol": {
      "lastModificationDate": 1753387626521,
      "contentHash": "da5a0c3bd86c896f6a407f909c57edf3",
      "sourceName": "@chainlink/contracts/src/v0.8/interfaces/LinkTokenInterface.sol",
      "solcConfig": {
        "version": "0.8.28",
        "settings": {
          "optimizer": {
            "enabled": true,
            "runs": 200
          },
          "viaIR": true,
          "evmVersion": "paris",
          "outputSelection": {
            "*": {
              "*": [
                "abi",
                "evm.bytecode",
                "evm.deployedBytecode",
                "evm.methodIdentifiers",
                "metadata"
              ],
              "": [
                "ast"
              ]
            }
          }
        }
      },
      "imports": [],
      "versionPragmas": [
        "^0.8.0"
      ],
      "artifacts": [
        "LinkTokenInterface"
      ]
    },
    "/Users/kimberleycheung/CiviXchain/civicxchain-platform/contracts/node_modules/@chainlink/contracts/src/v0.8/interfaces/PointerInterface.sol": {
      "lastModificationDate": 1753387626542,
      "contentHash": "27da4b2007d200dd5afff31dbf31ac99",
      "sourceName": "@chainlink/contracts/src/v0.8/interfaces/PointerInterface.sol",
      "solcConfig": {
        "version": "0.8.28",
        "settings": {
          "optimizer": {
            "enabled": true,
            "runs": 200
          },
          "viaIR": true,
          "evmVersion": "paris",
          "outputSelection": {
            "*": {
              "*": [
                "abi",
                "evm.bytecode",
                "evm.deployedBytecode",
                "evm.methodIdentifiers",
                "metadata"
              ],
              "": [
                "ast"
              ]
            }
          }
        }
      },
      "imports": [],
      "versionPragmas": [
        "^0.8.0"
      ],
      "artifacts": [
        "PointerInterface"
      ]
    },
    "/Users/kimberleycheung/CiviXchain/civicxchain-platform/contracts/node_modules/@chainlink/contracts/src/v0.8/interfaces/OperatorInterface.sol": {
      "lastModificationDate": 1753387626529,
      "contentHash": "e1822c36361fc3a26b5a68df3ddab15d",
      "sourceName": "@chainlink/contracts/src/v0.8/interfaces/OperatorInterface.sol",
      "solcConfig": {
        "version": "0.8.28",
        "settings": {
          "optimizer": {
            "enabled": true,
            "runs": 200
          },
          "viaIR": true,
          "evmVersion": "paris",
          "outputSelection": {
            "*": {
              "*": [
                "abi",
                "evm.bytecode",
                "evm.deployedBytecode",
                "evm.methodIdentifiers",
                "metadata"
              ],
              "": [
                "ast"
              ]
            }
          }
        }
      },
      "imports": [
        "./OracleInterface.sol",
        "./ChainlinkRequestInterface.sol"
      ],
      "versionPragmas": [
        "^0.8.0"
      ],
      "artifacts": [
        "OperatorInterface"
      ]
    },
    "/Users/kimberleycheung/CiviXchain/civicxchain-platform/contracts/node_modules/@chainlink/contracts/src/v0.8/interfaces/ENSInterface.sol": {
      "lastModificationDate": 1753387626473,
      "contentHash": "06b6aefcae95de6d1597ad8e1d73a08b",
      "sourceName": "@chainlink/contracts/src/v0.8/interfaces/ENSInterface.sol",
      "solcConfig": {
        "version": "0.8.28",
        "settings": {
          "optimizer": {
            "enabled": true,
            "runs": 200
          },
          "viaIR": true,
          "evmVersion": "paris",
          "outputSelection": {
            "*": {
              "*": [
                "abi",
                "evm.bytecode",
                "evm.deployedBytecode",
                "evm.methodIdentifiers",
                "metadata"
              ],
              "": [
                "ast"
              ]
            }
          }
        }
      },
      "imports": [],
      "versionPragmas": [
        "^0.8.0"
      ],
      "artifacts": [
        "ENSInterface"
      ]
    },
    "/Users/kimberleycheung/CiviXchain/civicxchain-platform/contracts/node_modules/@chainlink/contracts/src/v0.8/vendor/ENSResolver.sol": {
      "lastModificationDate": 1753387626474,
      "contentHash": "24a98b0606654e662097eed9ffa91a11",
      "sourceName": "@chainlink/contracts/src/v0.8/vendor/ENSResolver.sol",
      "solcConfig": {
        "version": "0.8.28",
        "settings": {
          "optimizer": {
            "enabled": true,
            "runs": 200
          },
          "viaIR": true,
          "evmVersion": "paris",
          "outputSelection": {
            "*": {
              "*": [
                "abi",
                "evm.bytecode",
                "evm.deployedBytecode",
                "evm.methodIdentifiers",
                "metadata"
              ],
              "": [
                "ast"
              ]
            }
          }
        }
      },
      "imports": [],
      "versionPragmas": [
        "^0.8.0"
      ],
      "artifacts": [
        "ENSResolver"
      ]
    },
    "/Users/kimberleycheung/CiviXchain/civicxchain-platform/contracts/node_modules/@chainlink/contracts/src/v0.8/vendor/CBORChainlink.sol": {
      "lastModificationDate": 1753387626446,
      "contentHash": "99b3ee2c29bc0d1a5cba583d9e8d835e",
      "sourceName": "@chainlink/contracts/src/v0.8/vendor/CBORChainlink.sol",
      "solcConfig": {
        "version": "0.8.28",
        "settings": {
          "optimizer": {
            "enabled": true,
            "runs": 200
          },
          "viaIR": true,
          "evmVersion": "paris",
          "outputSelection": {
            "*": {
              "*": [
                "abi",
                "evm.bytecode",
                "evm.deployedBytecode",
                "evm.methodIdentifiers",
                "metadata"
              ],
              "": [
                "ast"
              ]
            }
          }
        }
      },
      "imports": [
        "./BufferChainlink.sol"
      ],
      "versionPragmas": [
        ">=0.4.19"
      ],
      "artifacts": [
        "CBORChainlink"
      ]
    },
    "/Users/kimberleycheung/CiviXchain/civicxchain-platform/contracts/node_modules/@chainlink/contracts/src/v0.8/vendor/BufferChainlink.sol": {
      "lastModificationDate": 1753387626445,
      "contentHash": "52ac6f99fb0635751ae4ed11139878fd",
      "sourceName": "@chainlink/contracts/src/v0.8/vendor/BufferChainlink.sol",
      "solcConfig": {
        "version": "0.8.28",
        "settings": {
          "optimizer": {
            "enabled": true,
            "runs": 200
          },
          "viaIR": true,
          "evmVersion": "paris",
          "outputSelection": {
            "*": {
              "*": [
                "abi",
                "evm.bytecode",
                "evm.deployedBytecode",
                "evm.methodIdentifiers",
                "metadata"
              ],
              "": [
                "ast"
              ]
            }
          }
        }
      },
      "imports": [],
      "versionPragmas": [
        "^0.8.0"
      ],
      "artifacts": [
        "BufferChainlink"
      ]
    },
    "/Users/kimberleycheung/CiviXchain/civicxchain-platform/contracts/node_modules/@chainlink/contracts/src/v0.8/interfaces/OracleInterface.sol": {
      "lastModificationDate": 1753387626531,
      "contentHash": "6283e42024961596926c2b5015eef8e0",
      "sourceName": "@chainlink/contracts/src/v0.8/interfaces/OracleInterface.sol",
      "solcConfig": {
        "version": "0.8.28",
        "settings": {
          "optimizer": {
            "enabled": true,
            "runs": 200
          },
          "viaIR": true,
          "evmVersion": "paris",
          "outputSelection": {
            "*": {
              "*": [
                "abi",
                "evm.bytecode",
                "evm.deployedBytecode",
                "evm.methodIdentifiers",
                "metadata"
              ],
              "": [
                "ast"
              ]
            }
          }
        }
      },
      "imports": [],
      "versionPragmas": [
        "^0.8.0"
      ],
      "artifacts": [
        "OracleInterface"
      ]
    },
    "/Users/kimberleycheung/Desktop/CiviXchain5/civicxchain-platform/contracts/contracts/ChainlinkEnvironmentalOracle.sol": {
      "lastModificationDate": 1754066103221,
      "contentHash": "f95cee155f60d6c1cc83ed0a8149a0bf",
      "sourceName": "contracts/ChainlinkEnvironmentalOracle.sol",
      "solcConfig": {
        "version": "0.8.28",
        "settings": {
          "optimizer": {
            "enabled": true,
            "runs": 200
          },
          "viaIR": true,
          "evmVersion": "paris",
          "outputSelection": {
            "*": {
              "*": [
                "abi",
                "evm.bytecode",
                "evm.deployedBytecode",
                "evm.methodIdentifiers",
                "metadata"
              ],
              "": [
                "ast"
              ]
            }
          }
        }
      },
      "imports": [
        "@chainlink/contracts/src/v0.8/interfaces/AggregatorV3Interface.sol",
        "@chainlink/contracts/src/v0.8/ChainlinkClient.sol",
        "@chainlink/contracts/src/v0.8/ConfirmedOwner.sol"
      ],
      "versionPragmas": [
        "^0.8.19"
      ],
      "artifacts": [
        "ChainlinkEnvironmentalOracle"
      ]
    },
    "/Users/kimberleycheung/Desktop/CiviXchain5/civicxchain-platform/contracts/node_modules/@chainlink/contracts/src/v0.8/ChainlinkClient.sol": {
      "lastModificationDate": 1754066105533,
      "contentHash": "6af479cbde42f1a7225c9cebc6e32239",
      "sourceName": "@chainlink/contracts/src/v0.8/ChainlinkClient.sol",
      "solcConfig": {
        "version": "0.8.28",
        "settings": {
          "optimizer": {
            "enabled": true,
            "runs": 200
          },
          "viaIR": true,
          "evmVersion": "paris",
          "outputSelection": {
            "*": {
              "*": [
                "abi",
                "evm.bytecode",
                "evm.deployedBytecode",
                "evm.methodIdentifiers",
                "metadata"
              ],
              "": [
                "ast"
              ]
            }
          }
        }
      },
      "imports": [
        "./Chainlink.sol",
        "./interfaces/ENSInterface.sol",
        "./interfaces/LinkTokenInterface.sol",
        "./interfaces/ChainlinkRequestInterface.sol",
        "./interfaces/OperatorInterface.sol",
        "./interfaces/PointerInterface.sol",
        "./vendor/ENSResolver.sol"
      ],
      "versionPragmas": [
        "^0.8.0"
      ],
      "artifacts": [
        "ChainlinkClient"
      ]
    },
    "/Users/kimberleycheung/Desktop/CiviXchain5/civicxchain-platform/contracts/node_modules/@chainlink/contracts/src/v0.8/interfaces/AggregatorV3Interface.sol": {
      "lastModificationDate": 1754066105582,
      "contentHash": "d9654a0fc044a31d4106ee6bca772add",
      "sourceName": "@chainlink/contracts/src/v0.8/interfaces/AggregatorV3Interface.sol",
      "solcConfig": {
        "version": "0.8.28",
        "settings": {
          "optimizer": {
            "enabled": true,
            "runs": 200
          },
          "viaIR": true,
          "evmVersion": "paris",
          "outputSelection": {
            "*": {
              "*": [
                "abi",
                "evm.bytecode",
                "evm.deployedBytecode",
                "evm.methodIdentifiers",
                "metadata"
              ],
              "": [
                "ast"
              ]
            }
          }
        }
      },
      "imports": [],
      "versionPragmas": [
        "^0.8.0"
      ],
      "artifacts": [
        "AggregatorV3Interface"
      ]
    },
    "/Users/kimberleycheung/Desktop/CiviXchain5/civicxchain-platform/contracts/node_modules/@chainlink/contracts/src/v0.8/ConfirmedOwner.sol": {
      "lastModificationDate": 1754066105550,
      "contentHash": "16d64572b0310127fc8a771e63be6d20",
      "sourceName": "@chainlink/contracts/src/v0.8/ConfirmedOwner.sol",
      "solcConfig": {
        "version": "0.8.28",
        "settings": {
          "optimizer": {
            "enabled": true,
            "runs": 200
          },
          "viaIR": true,
          "evmVersion": "paris",
          "outputSelection": {
            "*": {
              "*": [
                "abi",
                "evm.bytecode",
                "evm.deployedBytecode",
                "evm.methodIdentifiers",
                "metadata"
              ],
              "": [
                "ast"
              ]
            }
          }
        }
      },
      "imports": [
        "./ConfirmedOwnerWithProposal.sol"
      ],
      "versionPragmas": [
        "^0.8.0"
      ],
      "artifacts": [
        "ConfirmedOwner"
      ]
    },
    "/Users/kimberleycheung/Desktop/CiviXchain5/civicxchain-platform/contracts/node_modules/@chainlink/contracts/src/v0.8/interfaces/ENSInterface.sol": {
      "lastModificationDate": 1754066105581,
      "contentHash": "06b6aefcae95de6d1597ad8e1d73a08b",
      "sourceName": "@chainlink/contracts/src/v0.8/interfaces/ENSInterface.sol",
      "solcConfig": {
        "version": "0.8.28",
        "settings": {
          "optimizer": {
            "enabled": true,
            "runs": 200
          },
          "viaIR": true,
          "evmVersion": "paris",
          "outputSelection": {
            "*": {
              "*": [
                "abi",
                "evm.bytecode",
                "evm.deployedBytecode",
                "evm.methodIdentifiers",
                "metadata"
              ],
              "": [
                "ast"
              ]
            }
          }
        }
      },
      "imports": [],
      "versionPragmas": [
        "^0.8.0"
      ],
      "artifacts": [
        "ENSInterface"
      ]
    },
    "/Users/kimberleycheung/Desktop/CiviXchain5/civicxchain-platform/contracts/node_modules/@chainlink/contracts/src/v0.8/interfaces/ChainlinkRequestInterface.sol": {
      "lastModificationDate": 1754066105581,
      "contentHash": "14407a6ead15cff8a0e0a7f8037c68f5",
      "sourceName": "@chainlink/contracts/src/v0.8/interfaces/ChainlinkRequestInterface.sol",
      "solcConfig": {
        "version": "0.8.28",
        "settings": {
          "optimizer": {
            "enabled": true,
            "runs": 200
          },
          "viaIR": true,
          "evmVersion": "paris",
          "outputSelection": {
            "*": {
              "*": [
                "abi",
                "evm.bytecode",
                "evm.deployedBytecode",
                "evm.methodIdentifiers",
                "metadata"
              ],
              "": [
                "ast"
              ]
            }
          }
        }
      },
      "imports": [],
      "versionPragmas": [
        "^0.8.0"
      ],
      "artifacts": [
        "ChainlinkRequestInterface"
      ]
    },
    "/Users/kimberleycheung/Desktop/CiviXchain5/civicxchain-platform/contracts/node_modules/@chainlink/contracts/src/v0.8/Chainlink.sol": {
      "lastModificationDate": 1754066105573,
      "contentHash": "9dc050539cdf1579d5650d41d0df9ec2",
      "sourceName": "@chainlink/contracts/src/v0.8/Chainlink.sol",
      "solcConfig": {
        "version": "0.8.28",
        "settings": {
          "optimizer": {
            "enabled": true,
            "runs": 200
          },
          "viaIR": true,
          "evmVersion": "paris",
          "outputSelection": {
            "*": {
              "*": [
                "abi",
                "evm.bytecode",
                "evm.deployedBytecode",
                "evm.methodIdentifiers",
                "metadata"
              ],
              "": [
                "ast"
              ]
            }
          }
        }
      },
      "imports": [
        "./vendor/CBORChainlink.sol",
        "./vendor/BufferChainlink.sol"
      ],
      "versionPragmas": [
        "^0.8.0"
      ],
      "artifacts": [
        "Chainlink"
      ]
    },
    "/Users/kimberleycheung/Desktop/CiviXchain5/civicxchain-platform/contracts/node_modules/@chainlink/contracts/src/v0.8/interfaces/LinkTokenInterface.sol": {
      "lastModificationDate": 1754066105580,
      "contentHash": "da5a0c3bd86c896f6a407f909c57edf3",
      "sourceName": "@chainlink/contracts/src/v0.8/interfaces/LinkTokenInterface.sol",
      "solcConfig": {
        "version": "0.8.28",
        "settings": {
          "optimizer": {
            "enabled": true,
            "runs": 200
          },
          "viaIR": true,
          "evmVersion": "paris",
          "outputSelection": {
            "*": {
              "*": [
                "abi",
                "evm.bytecode",
                "evm.deployedBytecode",
                "evm.methodIdentifiers",
                "metadata"
              ],
              "": [
                "ast"
              ]
            }
          }
        }
      },
      "imports": [],
      "versionPragmas": [
        "^0.8.0"
      ],
      "artifacts": [
        "LinkTokenInterface"
      ]
    },
    "/Users/kimberleycheung/Desktop/CiviXchain5/civicxchain-platform/contracts/node_modules/@chainlink/contracts/src/v0.8/interfaces/OperatorInterface.sol": {
      "lastModificationDate": 1754066105583,
      "contentHash": "e1822c36361fc3a26b5a68df3ddab15d",
      "sourceName": "@chainlink/contracts/src/v0.8/interfaces/OperatorInterface.sol",
      "solcConfig": {
        "version": "0.8.28",
        "settings": {
          "optimizer": {
            "enabled": true,
            "runs": 200
          },
          "viaIR": true,
          "evmVersion": "paris",
          "outputSelection": {
            "*": {
              "*": [
                "abi",
                "evm.bytecode",
                "evm.deployedBytecode",
                "evm.methodIdentifiers",
                "metadata"
              ],
              "": [
                "ast"
              ]
            }
          }
        }
      },
      "imports": [
        "./OracleInterface.sol",
        "./ChainlinkRequestInterface.sol"
      ],
      "versionPragmas": [
        "^0.8.0"
      ],
      "artifacts": [
        "OperatorInterface"
      ]
    },
    "/Users/kimberleycheung/Desktop/CiviXchain5/civicxchain-platform/contracts/node_modules/@chainlink/contracts/src/v0.8/interfaces/PointerInterface.sol": {
      "lastModificationDate": 1754066105581,
      "contentHash": "27da4b2007d200dd5afff31dbf31ac99",
      "sourceName": "@chainlink/contracts/src/v0.8/interfaces/PointerInterface.sol",
      "solcConfig": {
        "version": "0.8.28",
        "settings": {
          "optimizer": {
            "enabled": true,
            "runs": 200
          },
          "viaIR": true,
          "evmVersion": "paris",
          "outputSelection": {
            "*": {
              "*": [
                "abi",
                "evm.bytecode",
                "evm.deployedBytecode",
                "evm.methodIdentifiers",
                "metadata"
              ],
              "": [
                "ast"
              ]
            }
          }
        }
      },
      "imports": [],
      "versionPragmas": [
        "^0.8.0"
      ],
      "artifacts": [
        "PointerInterface"
      ]
    },
    "/Users/kimberleycheung/Desktop/CiviXchain5/civicxchain-platform/contracts/node_modules/@chainlink/contracts/src/v0.8/vendor/ENSResolver.sol": {
      "lastModificationDate": 1754066105580,
      "contentHash": "24a98b0606654e662097eed9ffa91a11",
      "sourceName": "@chainlink/contracts/src/v0.8/vendor/ENSResolver.sol",
      "solcConfig": {
        "version": "0.8.28",
        "settings": {
          "optimizer": {
            "enabled": true,
            "runs": 200
          },
          "viaIR": true,
          "evmVersion": "paris",
          "outputSelection": {
            "*": {
              "*": [
                "abi",
                "evm.bytecode",
                "evm.deployedBytecode",
                "evm.methodIdentifiers",
                "metadata"
              ],
              "": [
                "ast"
              ]
            }
          }
        }
      },
      "imports": [],
      "versionPragmas": [
        "^0.8.0"
      ],
      "artifacts": [
        "ENSResolver"
      ]
    },
    "/Users/kimberleycheung/Desktop/CiviXchain5/civicxchain-platform/contracts/node_modules/@chainlink/contracts/src/v0.8/vendor/CBORChainlink.sol": {
      "lastModificationDate": 1754066105579,
      "contentHash": "99b3ee2c29bc0d1a5cba583d9e8d835e",
      "sourceName": "@chainlink/contracts/src/v0.8/vendor/CBORChainlink.sol",
      "solcConfig": {
        "version": "0.8.28",
        "settings": {
          "optimizer": {
            "enabled": true,
            "runs": 200
          },
          "viaIR": true,
          "evmVersion": "paris",
          "outputSelection": {
            "*": {
              "*": [
                "abi",
                "evm.bytecode",
                "evm.deployedBytecode",
                "evm.methodIdentifiers",
                "metadata"
              ],
              "": [
                "ast"
              ]
            }
          }
        }
      },
      "imports": [
        "./BufferChainlink.sol"
      ],
      "versionPragmas": [
        ">=0.4.19"
      ],
      "artifacts": [
        "CBORChainlink"
      ]
    },
    "/Users/kimberleycheung/Desktop/CiviXchain5/civicxchain-platform/contracts/node_modules/@chainlink/contracts/src/v0.8/vendor/BufferChainlink.sol": {
      "lastModificationDate": 1754066105578,
      "contentHash": "52ac6f99fb0635751ae4ed11139878fd",
      "sourceName": "@chainlink/contracts/src/v0.8/vendor/BufferChainlink.sol",
      "solcConfig": {
        "version": "0.8.28",
        "settings": {
          "optimizer": {
            "enabled": true,
            "runs": 200
          },
          "viaIR": true,
          "evmVersion": "paris",
          "outputSelection": {
            "*": {
              "*": [
                "abi",
                "evm.bytecode",
                "evm.deployedBytecode",
                "evm.methodIdentifiers",
                "metadata"
              ],
              "": [
                "ast"
              ]
            }
          }
        }
      },
      "imports": [],
      "versionPragmas": [
        "^0.8.0"
      ],
      "artifacts": [
        "BufferChainlink"
      ]
    },
    "/Users/kimberleycheung/Desktop/CiviXchain5/civicxchain-platform/contracts/node_modules/@chainlink/contracts/src/v0.8/interfaces/OracleInterface.sol": {
      "lastModificationDate": 1754066105583,
      "contentHash": "6283e42024961596926c2b5015eef8e0",
      "sourceName": "@chainlink/contracts/src/v0.8/interfaces/OracleInterface.sol",
      "solcConfig": {
        "version": "0.8.28",
        "settings": {
          "optimizer": {
            "enabled": true,
            "runs": 200
          },
          "viaIR": true,
          "evmVersion": "paris",
          "outputSelection": {
            "*": {
              "*": [
                "abi",
                "evm.bytecode",
                "evm.deployedBytecode",
                "evm.methodIdentifiers",
                "metadata"
              ],
              "": [
                "ast"
              ]
            }
          }
        }
      },
      "imports": [],
      "versionPragmas": [
        "^0.8.0"
      ],
      "artifacts": [
        "OracleInterface"
      ]
    },
    "/Users/kimberleycheung/Desktop/CiviXchain5/civicxchain-platform/contracts/node_modules/@chainlink/contracts/src/v0.8/ConfirmedOwnerWithProposal.sol": {
      "lastModificationDate": 1754066105554,
      "contentHash": "8b1c5f02622cd87472493bda6595d1be",
      "sourceName": "@chainlink/contracts/src/v0.8/ConfirmedOwnerWithProposal.sol",
      "solcConfig": {
        "version": "0.8.28",
        "settings": {
          "optimizer": {
            "enabled": true,
            "runs": 200
          },
          "viaIR": true,
          "evmVersion": "paris",
          "outputSelection": {
            "*": {
              "*": [
                "abi",
                "evm.bytecode",
                "evm.deployedBytecode",
                "evm.methodIdentifiers",
                "metadata"
              ],
              "": [
                "ast"
              ]
            }
          }
        }
      },
      "imports": [
        "./interfaces/OwnableInterface.sol"
      ],
      "versionPragmas": [
        "^0.8.0"
      ],
      "artifacts": [
        "ConfirmedOwnerWithProposal"
      ]
    },
    "/Users/kimberleycheung/Desktop/CiviXchain5/civicxchain-platform/contracts/node_modules/@chainlink/contracts/src/v0.8/interfaces/OwnableInterface.sol": {
      "lastModificationDate": 1754066105584,
      "contentHash": "2e814c8a9f77897f6995436d97c23d99",
      "sourceName": "@chainlink/contracts/src/v0.8/interfaces/OwnableInterface.sol",
      "solcConfig": {
        "version": "0.8.28",
        "settings": {
          "optimizer": {
            "enabled": true,
            "runs": 200
          },
          "viaIR": true,
          "evmVersion": "paris",
          "outputSelection": {
            "*": {
              "*": [
                "abi",
                "evm.bytecode",
                "evm.deployedBytecode",
                "evm.methodIdentifiers",
                "metadata"
              ],
              "": [
                "ast"
              ]
            }
          }
        }
      },
      "imports": [],
      "versionPragmas": [
        "^0.8.0"
      ],
      "artifacts": [
        "OwnableInterface"
      ]
    },
    "/Users/kimberleycheung/Desktop/CiviXchain5/civicxchain-platform/contracts/contracts/RealEnvironmentalOracle.sol": {
      "lastModificationDate": 1754066103221,
      "contentHash": "99181dec03a4e0bda6f5566b4fc6a2a0",
      "sourceName": "contracts/RealEnvironmentalOracle.sol",
      "solcConfig": {
        "version": "0.8.28",
        "settings": {
          "optimizer": {
            "enabled": true,
            "runs": 200
          },
          "viaIR": true,
          "evmVersion": "paris",
          "outputSelection": {
            "*": {
              "*": [
                "abi",
                "evm.bytecode",
                "evm.deployedBytecode",
                "evm.methodIdentifiers",
                "metadata"
              ],
              "": [
                "ast"
              ]
            }
          }
        }
      },
      "imports": [
        "@chainlink/contracts/src/v0.8/interfaces/AggregatorV3Interface.sol"
      ],
      "versionPragmas": [
        "^0.8.19"
      ],
      "artifacts": [
        "RealEnvironmentalOracle"
      ]
    },
    "/Users/kimberleycheung/Desktop/CiviXchain5/civicxchain-platform/contracts/contracts/CivicXChainGovernance.sol": {
      "lastModificationDate": 1754343673501,
      "contentHash": "e40c5fcaaab3a1710046d75b22acf227",
      "sourceName": "contracts/CivicXChainGovernance.sol",
      "solcConfig": {
        "version": "0.8.28",
        "settings": {
          "optimizer": {
            "enabled": true,
            "runs": 200
          },
          "viaIR": true,
          "evmVersion": "paris",
          "outputSelection": {
            "*": {
              "*": [
                "abi",
                "evm.bytecode",
                "evm.deployedBytecode",
                "evm.methodIdentifiers",
                "metadata"
              ],
              "": [
                "ast"
              ]
            }
          }
        }
      },
      "imports": [
        "@openzeppelin/contracts/token/ERC20/ERC20.sol",
        "@openzeppelin/contracts/access/Ownable.sol",
        "@openzeppelin/contracts/security/ReentrancyGuard.sol",
        "@chainlink/contracts/src/v0.8/interfaces/AggregatorV3Interface.sol"
      ],
      "versionPragmas": [
        "^0.8.19"
      ],
      "artifacts": [
        "CivicXChainGovernance"
      ]
    },
    "/Users/kimberleycheung/Desktop/CiviXchain5/civicxchain-platform/contracts/node_modules/@openzeppelin/contracts/security/ReentrancyGuard.sol": {
      "lastModificationDate": 1754066108551,
      "contentHash": "1535f8c0c68463f8c1b5239f7584e71f",
      "sourceName": "@openzeppelin/contracts/security/ReentrancyGuard.sol",
      "solcConfig": {
        "version": "0.8.28",
        "settings": {
          "optimizer": {
            "enabled": true,
            "runs": 200
          },
          "viaIR": true,
          "evmVersion": "paris",
          "outputSelection": {
            "*": {
              "*": [
                "abi",
                "evm.bytecode",
                "evm.deployedBytecode",
                "evm.methodIdentifiers",
                "metadata"
              ],
              "": [
                "ast"
              ]
            }
          }
        }
      },
      "imports": [],
      "versionPragmas": [
        "^0.8.0"
      ],
      "artifacts": [
        "ReentrancyGuard"
      ]
    },
    "/Users/kimberleycheung/Desktop/CiviXchain5/civicxchain-platform/contracts/node_modules/@openzeppelin/contracts/access/Ownable.sol": {
      "lastModificationDate": 1754066108550,
      "contentHash": "5a20b2cad87ddb61c7a3a6af21289e28",
      "sourceName": "@openzeppelin/contracts/access/Ownable.sol",
      "solcConfig": {
        "version": "0.8.28",
        "settings": {
          "optimizer": {
            "enabled": true,
            "runs": 200
          },
          "viaIR": true,
          "evmVersion": "paris",
          "outputSelection": {
            "*": {
              "*": [
                "abi",
                "evm.bytecode",
                "evm.deployedBytecode",
                "evm.methodIdentifiers",
                "metadata"
              ],
              "": [
                "ast"
              ]
            }
          }
        }
      },
      "imports": [
        "../utils/Context.sol"
      ],
      "versionPragmas": [
        "^0.8.0"
      ],
      "artifacts": [
        "Ownable"
      ]
    },
    "/Users/kimberleycheung/Desktop/CiviXchain5/civicxchain-platform/contracts/node_modules/@openzeppelin/contracts/token/ERC20/ERC20.sol": {
      "lastModificationDate": 1754066108531,
      "contentHash": "3ae5166c6827a9cf1a7a462d1632b464",
      "sourceName": "@openzeppelin/contracts/token/ERC20/ERC20.sol",
      "solcConfig": {
        "version": "0.8.28",
        "settings": {
          "optimizer": {
            "enabled": true,
            "runs": 200
          },
          "viaIR": true,
          "evmVersion": "paris",
          "outputSelection": {
            "*": {
              "*": [
                "abi",
                "evm.bytecode",
                "evm.deployedBytecode",
                "evm.methodIdentifiers",
                "metadata"
              ],
              "": [
                "ast"
              ]
            }
          }
        }
      },
      "imports": [
        "./IERC20.sol",
        "./extensions/IERC20Metadata.sol",
        "../../utils/Context.sol"
      ],
      "versionPragmas": [
        "^0.8.0"
      ],
      "artifacts": [
        "ERC20"
      ]
    },
    "/Users/kimberleycheung/Desktop/CiviXchain5/civicxchain-platform/contracts/node_modules/@openzeppelin/contracts/utils/Context.sol": {
      "lastModificationDate": 1754066108563,
      "contentHash": "f07feb4a44b1a4872370da5aa70e8e46",
      "sourceName": "@openzeppelin/contracts/utils/Context.sol",
      "solcConfig": {
        "version": "0.8.28",
        "settings": {
          "optimizer": {
            "enabled": true,
            "runs": 200
          },
          "viaIR": true,
          "evmVersion": "paris",
          "outputSelection": {
            "*": {
              "*": [
                "abi",
                "evm.bytecode",
                "evm.deployedBytecode",
                "evm.methodIdentifiers",
                "metadata"
              ],
              "": [
                "ast"
              ]
            }
          }
        }
      },
      "imports": [],
      "versionPragmas": [
        "^0.8.0"
      ],
      "artifacts": [
        "Context"
      ]
    },
    "/Users/kimberleycheung/Desktop/CiviXchain5/civicxchain-platform/contracts/node_modules/@openzeppelin/contracts/token/ERC20/IERC20.sol": {
      "lastModificationDate": 1754066108531,
      "contentHash": "df36f7051335cd1e748b1b6463b7fdd3",
      "sourceName": "@openzeppelin/contracts/token/ERC20/IERC20.sol",
      "solcConfig": {
        "version": "0.8.28",
        "settings": {
          "optimizer": {
            "enabled": true,
            "runs": 200
          },
          "viaIR": true,
          "evmVersion": "paris",
          "outputSelection": {
            "*": {
              "*": [
                "abi",
                "evm.bytecode",
                "evm.deployedBytecode",
                "evm.methodIdentifiers",
                "metadata"
              ],
              "": [
                "ast"
              ]
            }
          }
        }
      },
      "imports": [],
      "versionPragmas": [
        "^0.8.0"
      ],
      "artifacts": [
        "IERC20"
      ]
    },
    "/Users/kimberleycheung/Desktop/CiviXchain5/civicxchain-platform/contracts/node_modules/@openzeppelin/contracts/token/ERC20/extensions/IERC20Metadata.sol": {
      "lastModificationDate": 1754066108533,
      "contentHash": "909ab67fc5c25033fe6cd364f8c056f9",
      "sourceName": "@openzeppelin/contracts/token/ERC20/extensions/IERC20Metadata.sol",
      "solcConfig": {
        "version": "0.8.28",
        "settings": {
          "optimizer": {
            "enabled": true,
            "runs": 200
          },
          "viaIR": true,
          "evmVersion": "paris",
          "outputSelection": {
            "*": {
              "*": [
                "abi",
                "evm.bytecode",
                "evm.deployedBytecode",
                "evm.methodIdentifiers",
                "metadata"
              ],
              "": [
                "ast"
              ]
            }
          }
        }
      },
      "imports": [
        "../IERC20.sol"
      ],
      "versionPragmas": [
        "^0.8.0"
      ],
      "artifacts": [
        "IERC20Metadata"
      ]
    },
    "/Users/kimberleycheung/Desktop/CiviXchain5/civicxchain-platform/contracts/contracts/EnvironmentalDataOracle.sol": {
      "lastModificationDate": 1754066103220,
      "contentHash": "1330cc3ce108354a9c134c0ace5ac977",
      "sourceName": "contracts/EnvironmentalDataOracle.sol",
      "solcConfig": {
        "version": "0.8.28",
        "settings": {
          "optimizer": {
            "enabled": true,
            "runs": 200
          },
          "viaIR": true,
          "evmVersion": "paris",
          "outputSelection": {
            "*": {
              "*": [
                "abi",
                "evm.bytecode",
                "evm.deployedBytecode",
                "evm.methodIdentifiers",
                "metadata"
              ],
              "": [
                "ast"
              ]
            }
          }
        }
      },
      "imports": [],
      "versionPragmas": [
        "^0.8.19"
      ],
      "artifacts": [
        "EnvironmentalDataOracle"
      ]
    },
    "/Users/kimberleycheung/Desktop/CiviXchain8/civicxchain-platform/contracts/contracts/ChainlinkEnvironmentalOracle.sol": {
      "lastModificationDate": 1755096489584,
      "contentHash": "f95cee155f60d6c1cc83ed0a8149a0bf",
      "sourceName": "contracts/ChainlinkEnvironmentalOracle.sol",
      "solcConfig": {
        "version": "0.8.28",
        "settings": {
          "optimizer": {
            "enabled": true,
            "runs": 200
          },
          "viaIR": true,
          "evmVersion": "paris",
          "outputSelection": {
            "*": {
              "*": [
                "abi",
                "evm.bytecode",
                "evm.deployedBytecode",
                "evm.methodIdentifiers",
                "metadata"
              ],
              "": [
                "ast"
              ]
            }
          }
        }
      },
      "imports": [
        "@chainlink/contracts/src/v0.8/interfaces/AggregatorV3Interface.sol",
        "@chainlink/contracts/src/v0.8/ChainlinkClient.sol",
        "@chainlink/contracts/src/v0.8/ConfirmedOwner.sol"
      ],
      "versionPragmas": [
        "^0.8.19"
      ],
      "artifacts": [
        "ChainlinkEnvironmentalOracle"
      ]
    },
    "/Users/kimberleycheung/Desktop/CiviXchain8/civicxchain-platform/contracts/node_modules/@chainlink/contracts/src/v0.8/ConfirmedOwner.sol": {
      "lastModificationDate": 1755096491883,
      "contentHash": "16d64572b0310127fc8a771e63be6d20",
      "sourceName": "@chainlink/contracts/src/v0.8/ConfirmedOwner.sol",
      "solcConfig": {
        "version": "0.8.28",
        "settings": {
          "optimizer": {
            "enabled": true,
            "runs": 200
          },
          "viaIR": true,
          "evmVersion": "paris",
          "outputSelection": {
            "*": {
              "*": [
                "abi",
                "evm.bytecode",
                "evm.deployedBytecode",
                "evm.methodIdentifiers",
                "metadata"
              ],
              "": [
                "ast"
              ]
            }
          }
        }
      },
      "imports": [
        "./ConfirmedOwnerWithProposal.sol"
      ],
      "versionPragmas": [
        "^0.8.0"
      ],
      "artifacts": [
        "ConfirmedOwner"
      ]
    },
    "/Users/kimberleycheung/Desktop/CiviXchain8/civicxchain-platform/contracts/node_modules/@chainlink/contracts/src/v0.8/ChainlinkClient.sol": {
      "lastModificationDate": 1755096491865,
      "contentHash": "6af479cbde42f1a7225c9cebc6e32239",
      "sourceName": "@chainlink/contracts/src/v0.8/ChainlinkClient.sol",
      "solcConfig": {
        "version": "0.8.28",
        "settings": {
          "optimizer": {
            "enabled": true,
            "runs": 200
          },
          "viaIR": true,
          "evmVersion": "paris",
          "outputSelection": {
            "*": {
              "*": [
                "abi",
                "evm.bytecode",
                "evm.deployedBytecode",
                "evm.methodIdentifiers",
                "metadata"
              ],
              "": [
                "ast"
              ]
            }
          }
        }
      },
      "imports": [
        "./Chainlink.sol",
        "./interfaces/ENSInterface.sol",
        "./interfaces/LinkTokenInterface.sol",
        "./interfaces/ChainlinkRequestInterface.sol",
        "./interfaces/OperatorInterface.sol",
        "./interfaces/PointerInterface.sol",
        "./vendor/ENSResolver.sol"
      ],
      "versionPragmas": [
        "^0.8.0"
      ],
      "artifacts": [
        "ChainlinkClient"
      ]
    },
    "/Users/kimberleycheung/Desktop/CiviXchain8/civicxchain-platform/contracts/node_modules/@chainlink/contracts/src/v0.8/interfaces/AggregatorV3Interface.sol": {
      "lastModificationDate": 1755096491918,
      "contentHash": "d9654a0fc044a31d4106ee6bca772add",
      "sourceName": "@chainlink/contracts/src/v0.8/interfaces/AggregatorV3Interface.sol",
      "solcConfig": {
        "version": "0.8.28",
        "settings": {
          "optimizer": {
            "enabled": true,
            "runs": 200
          },
          "viaIR": true,
          "evmVersion": "paris",
          "outputSelection": {
            "*": {
              "*": [
                "abi",
                "evm.bytecode",
                "evm.deployedBytecode",
                "evm.methodIdentifiers",
                "metadata"
              ],
              "": [
                "ast"
              ]
            }
          }
        }
      },
      "imports": [],
      "versionPragmas": [
        "^0.8.0"
      ],
      "artifacts": [
        "AggregatorV3Interface"
      ]
    },
    "/Users/kimberleycheung/Desktop/CiviXchain8/civicxchain-platform/contracts/node_modules/@chainlink/contracts/src/v0.8/ConfirmedOwnerWithProposal.sol": {
      "lastModificationDate": 1755096491886,
      "contentHash": "8b1c5f02622cd87472493bda6595d1be",
      "sourceName": "@chainlink/contracts/src/v0.8/ConfirmedOwnerWithProposal.sol",
      "solcConfig": {
        "version": "0.8.28",
        "settings": {
          "optimizer": {
            "enabled": true,
            "runs": 200
          },
          "viaIR": true,
          "evmVersion": "paris",
          "outputSelection": {
            "*": {
              "*": [
                "abi",
                "evm.bytecode",
                "evm.deployedBytecode",
                "evm.methodIdentifiers",
                "metadata"
              ],
              "": [
                "ast"
              ]
            }
          }
        }
      },
      "imports": [
        "./interfaces/OwnableInterface.sol"
      ],
      "versionPragmas": [
        "^0.8.0"
      ],
      "artifacts": [
        "ConfirmedOwnerWithProposal"
      ]
    },
    "/Users/kimberleycheung/Desktop/CiviXchain8/civicxchain-platform/contracts/node_modules/@chainlink/contracts/src/v0.8/interfaces/OwnableInterface.sol": {
      "lastModificationDate": 1755096491919,
      "contentHash": "2e814c8a9f77897f6995436d97c23d99",
      "sourceName": "@chainlink/contracts/src/v0.8/interfaces/OwnableInterface.sol",
      "solcConfig": {
        "version": "0.8.28",
        "settings": {
          "optimizer": {
            "enabled": true,
            "runs": 200
          },
          "viaIR": true,
          "evmVersion": "paris",
          "outputSelection": {
            "*": {
              "*": [
                "abi",
                "evm.bytecode",
                "evm.deployedBytecode",
                "evm.methodIdentifiers",
                "metadata"
              ],
              "": [
                "ast"
              ]
            }
          }
        }
      },
      "imports": [],
      "versionPragmas": [
        "^0.8.0"
      ],
      "artifacts": [
        "OwnableInterface"
      ]
    },
    "/Users/kimberleycheung/Desktop/CiviXchain8/civicxchain-platform/contracts/node_modules/@chainlink/contracts/src/v0.8/Chainlink.sol": {
      "lastModificationDate": 1755096491907,
      "contentHash": "9dc050539cdf1579d5650d41d0df9ec2",
      "sourceName": "@chainlink/contracts/src/v0.8/Chainlink.sol",
      "solcConfig": {
        "version": "0.8.28",
        "settings": {
          "optimizer": {
            "enabled": true,
            "runs": 200
          },
          "viaIR": true,
          "evmVersion": "paris",
          "outputSelection": {
            "*": {
              "*": [
                "abi",
                "evm.bytecode",
                "evm.deployedBytecode",
                "evm.methodIdentifiers",
                "metadata"
              ],
              "": [
                "ast"
              ]
            }
          }
        }
      },
      "imports": [
        "./vendor/CBORChainlink.sol",
        "./vendor/BufferChainlink.sol"
      ],
      "versionPragmas": [
        "^0.8.0"
      ],
      "artifacts": [
        "Chainlink"
      ]
    },
    "/Users/kimberleycheung/Desktop/CiviXchain8/civicxchain-platform/contracts/node_modules/@chainlink/contracts/src/v0.8/interfaces/ChainlinkRequestInterface.sol": {
      "lastModificationDate": 1755096491917,
      "contentHash": "14407a6ead15cff8a0e0a7f8037c68f5",
      "sourceName": "@chainlink/contracts/src/v0.8/interfaces/ChainlinkRequestInterface.sol",
      "solcConfig": {
        "version": "0.8.28",
        "settings": {
          "optimizer": {
            "enabled": true,
            "runs": 200
          },
          "viaIR": true,
          "evmVersion": "paris",
          "outputSelection": {
            "*": {
              "*": [
                "abi",
                "evm.bytecode",
                "evm.deployedBytecode",
                "evm.methodIdentifiers",
                "metadata"
              ],
              "": [
                "ast"
              ]
            }
          }
        }
      },
      "imports": [],
      "versionPragmas": [
        "^0.8.0"
      ],
      "artifacts": [
        "ChainlinkRequestInterface"
      ]
    },
    "/Users/kimberleycheung/Desktop/CiviXchain8/civicxchain-platform/contracts/node_modules/@chainlink/contracts/src/v0.8/interfaces/LinkTokenInterface.sol": {
      "lastModificationDate": 1755096491916,
      "contentHash": "da5a0c3bd86c896f6a407f909c57edf3",
      "sourceName": "@chainlink/contracts/src/v0.8/interfaces/LinkTokenInterface.sol",
      "solcConfig": {
        "version": "0.8.28",
        "settings": {
          "optimizer": {
            "enabled": true,
            "runs": 200
          },
          "viaIR": true,
          "evmVersion": "paris",
          "outputSelection": {
            "*": {
              "*": [
                "abi",
                "evm.bytecode",
                "evm.deployedBytecode",
                "evm.methodIdentifiers",
                "metadata"
              ],
              "": [
                "ast"
              ]
            }
          }
        }
      },
      "imports": [],
      "versionPragmas": [
        "^0.8.0"
      ],
      "artifacts": [
        "LinkTokenInterface"
      ]
    },
    "/Users/kimberleycheung/Desktop/CiviXchain8/civicxchain-platform/contracts/node_modules/@chainlink/contracts/src/v0.8/interfaces/ENSInterface.sol": {
      "lastModificationDate": 1755096491917,
      "contentHash": "06b6aefcae95de6d1597ad8e1d73a08b",
      "sourceName": "@chainlink/contracts/src/v0.8/interfaces/ENSInterface.sol",
      "solcConfig": {
        "version": "0.8.28",
        "settings": {
          "optimizer": {
            "enabled": true,
            "runs": 200
          },
          "viaIR": true,
          "evmVersion": "paris",
          "outputSelection": {
            "*": {
              "*": [
                "abi",
                "evm.bytecode",
                "evm.deployedBytecode",
                "evm.methodIdentifiers",
                "metadata"
              ],
              "": [
                "ast"
              ]
            }
          }
        }
      },
      "imports": [],
      "versionPragmas": [
        "^0.8.0"
      ],
      "artifacts": [
        "ENSInterface"
      ]
    },
    "/Users/kimberleycheung/Desktop/CiviXchain8/civicxchain-platform/contracts/node_modules/@chainlink/contracts/src/v0.8/interfaces/OperatorInterface.sol": {
      "lastModificationDate": 1755096491918,
      "contentHash": "e1822c36361fc3a26b5a68df3ddab15d",
      "sourceName": "@chainlink/contracts/src/v0.8/interfaces/OperatorInterface.sol",
      "solcConfig": {
        "version": "0.8.28",
        "settings": {
          "optimizer": {
            "enabled": true,
            "runs": 200
          },
          "viaIR": true,
          "evmVersion": "paris",
          "outputSelection": {
            "*": {
              "*": [
                "abi",
                "evm.bytecode",
                "evm.deployedBytecode",
                "evm.methodIdentifiers",
                "metadata"
              ],
              "": [
                "ast"
              ]
            }
          }
        }
      },
      "imports": [
        "./OracleInterface.sol",
        "./ChainlinkRequestInterface.sol"
      ],
      "versionPragmas": [
        "^0.8.0"
      ],
      "artifacts": [
        "OperatorInterface"
      ]
    },
    "/Users/kimberleycheung/Desktop/CiviXchain8/civicxchain-platform/contracts/node_modules/@chainlink/contracts/src/v0.8/vendor/ENSResolver.sol": {
      "lastModificationDate": 1755096491915,
      "contentHash": "24a98b0606654e662097eed9ffa91a11",
      "sourceName": "@chainlink/contracts/src/v0.8/vendor/ENSResolver.sol",
      "solcConfig": {
        "version": "0.8.28",
        "settings": {
          "optimizer": {
            "enabled": true,
            "runs": 200
          },
          "viaIR": true,
          "evmVersion": "paris",
          "outputSelection": {
            "*": {
              "*": [
                "abi",
                "evm.bytecode",
                "evm.deployedBytecode",
                "evm.methodIdentifiers",
                "metadata"
              ],
              "": [
                "ast"
              ]
            }
          }
        }
      },
      "imports": [],
      "versionPragmas": [
        "^0.8.0"
      ],
      "artifacts": [
        "ENSResolver"
      ]
    },
    "/Users/kimberleycheung/Desktop/CiviXchain8/civicxchain-platform/contracts/node_modules/@chainlink/contracts/src/v0.8/interfaces/PointerInterface.sol": {
      "lastModificationDate": 1755096491917,
      "contentHash": "27da4b2007d200dd5afff31dbf31ac99",
      "sourceName": "@chainlink/contracts/src/v0.8/interfaces/PointerInterface.sol",
      "solcConfig": {
        "version": "0.8.28",
        "settings": {
          "optimizer": {
            "enabled": true,
            "runs": 200
          },
          "viaIR": true,
          "evmVersion": "paris",
          "outputSelection": {
            "*": {
              "*": [
                "abi",
                "evm.bytecode",
                "evm.deployedBytecode",
                "evm.methodIdentifiers",
                "metadata"
              ],
              "": [
                "ast"
              ]
            }
          }
        }
      },
      "imports": [],
      "versionPragmas": [
        "^0.8.0"
      ],
      "artifacts": [
        "PointerInterface"
      ]
    },
    "/Users/kimberleycheung/Desktop/CiviXchain8/civicxchain-platform/contracts/node_modules/@chainlink/contracts/src/v0.8/vendor/CBORChainlink.sol": {
      "lastModificationDate": 1755096491915,
      "contentHash": "99b3ee2c29bc0d1a5cba583d9e8d835e",
      "sourceName": "@chainlink/contracts/src/v0.8/vendor/CBORChainlink.sol",
      "solcConfig": {
        "version": "0.8.28",
        "settings": {
          "optimizer": {
            "enabled": true,
            "runs": 200
          },
          "viaIR": true,
          "evmVersion": "paris",
          "outputSelection": {
            "*": {
              "*": [
                "abi",
                "evm.bytecode",
                "evm.deployedBytecode",
                "evm.methodIdentifiers",
                "metadata"
              ],
              "": [
                "ast"
              ]
            }
          }
        }
      },
      "imports": [
        "./BufferChainlink.sol"
      ],
      "versionPragmas": [
        ">=0.4.19"
      ],
      "artifacts": [
        "CBORChainlink"
      ]
    },
    "/Users/kimberleycheung/Desktop/CiviXchain8/civicxchain-platform/contracts/node_modules/@chainlink/contracts/src/v0.8/vendor/BufferChainlink.sol": {
      "lastModificationDate": 1755096491914,
      "contentHash": "52ac6f99fb0635751ae4ed11139878fd",
      "sourceName": "@chainlink/contracts/src/v0.8/vendor/BufferChainlink.sol",
      "solcConfig": {
        "version": "0.8.28",
        "settings": {
          "optimizer": {
            "enabled": true,
            "runs": 200
          },
          "viaIR": true,
          "evmVersion": "paris",
          "outputSelection": {
            "*": {
              "*": [
                "abi",
                "evm.bytecode",
                "evm.deployedBytecode",
                "evm.methodIdentifiers",
                "metadata"
              ],
              "": [
                "ast"
              ]
            }
          }
        }
      },
      "imports": [],
      "versionPragmas": [
        "^0.8.0"
      ],
      "artifacts": [
        "BufferChainlink"
      ]
    },
    "/Users/kimberleycheung/Desktop/CiviXchain8/civicxchain-platform/contracts/node_modules/@chainlink/contracts/src/v0.8/interfaces/OracleInterface.sol": {
      "lastModificationDate": 1755096491919,
      "contentHash": "6283e42024961596926c2b5015eef8e0",
      "sourceName": "@chainlink/contracts/src/v0.8/interfaces/OracleInterface.sol",
      "solcConfig": {
        "version": "0.8.28",
        "settings": {
          "optimizer": {
            "enabled": true,
            "runs": 200
          },
          "viaIR": true,
          "evmVersion": "paris",
          "outputSelection": {
            "*": {
              "*": [
                "abi",
                "evm.bytecode",
                "evm.deployedBytecode",
                "evm.methodIdentifiers",
                "metadata"
              ],
              "": [
                "ast"
              ]
            }
          }
        }
      },
      "imports": [],
      "versionPragmas": [
        "^0.8.0"
      ],
      "artifacts": [
        "OracleInterface"
      ]
    },
    "/Users/kimberleycheung/Desktop/CiviXchain8/civicxchain-platform/contracts/contracts/OracleManager.sol": {
      "lastModificationDate": 1755189274574,
      "contentHash": "7bbb0214bcba0c84af09562e18b4c43c",
      "sourceName": "contracts/OracleManager.sol",
      "solcConfig": {
        "version": "0.8.28",
        "settings": {
          "optimizer": {
            "enabled": true,
            "runs": 200
          },
          "viaIR": true,
          "evmVersion": "paris",
          "outputSelection": {
            "*": {
              "*": [
                "abi",
                "evm.bytecode",
                "evm.deployedBytecode",
                "evm.methodIdentifiers",
                "metadata"
              ],
              "": [
                "ast"
              ]
            }
          }
        }
      },
      "imports": [
        "@chainlink/contracts/src/v0.8/interfaces/AggregatorV3Interface.sol",
        "./ChainlinkEnvironmentalOracle.sol",
        "./RealEnvironmentalOracle.sol"
      ],
      "versionPragmas": [
        "^0.8.19"
      ],
      "artifacts": [
        "OracleManager"
      ]
    },
    "/Users/kimberleycheung/Desktop/CiviXchain8/civicxchain-platform/contracts/contracts/RealEnvironmentalOracle.sol": {
      "lastModificationDate": 1755096489584,
      "contentHash": "99181dec03a4e0bda6f5566b4fc6a2a0",
      "sourceName": "contracts/RealEnvironmentalOracle.sol",
      "solcConfig": {
        "version": "0.8.28",
        "settings": {
          "optimizer": {
            "enabled": true,
            "runs": 200
          },
          "viaIR": true,
          "evmVersion": "paris",
          "outputSelection": {
            "*": {
              "*": [
                "abi",
                "evm.bytecode",
                "evm.deployedBytecode",
                "evm.methodIdentifiers",
                "metadata"
              ],
              "": [
                "ast"
              ]
            }
          }
        }
      },
      "imports": [
        "@chainlink/contracts/src/v0.8/interfaces/AggregatorV3Interface.sol"
      ],
      "versionPragmas": [
        "^0.8.19"
      ],
      "artifacts": [
        "RealEnvironmentalOracle"
      ]
    },
    "/Users/kimberleycheung/Desktop/CiviXchain8/civicxchain-platform/contracts/contracts/CivicXChainGovernance.sol": {
      "lastModificationDate": 1755115046866,
      "contentHash": "10c2aa37f856cbdf96f561599a471744",
      "sourceName": "contracts/CivicXChainGovernance.sol",
      "solcConfig": {
        "version": "0.8.28",
        "settings": {
          "optimizer": {
            "enabled": true,
            "runs": 200
          },
          "viaIR": true,
          "evmVersion": "paris",
          "outputSelection": {
            "*": {
              "*": [
                "abi",
                "evm.bytecode",
                "evm.deployedBytecode",
                "evm.methodIdentifiers",
                "metadata"
              ],
              "": [
                "ast"
              ]
            }
          }
        }
      },
      "imports": [
        "@openzeppelin/contracts/token/ERC20/ERC20.sol",
        "@openzeppelin/contracts/access/Ownable.sol",
        "@openzeppelin/contracts/security/ReentrancyGuard.sol",
        "@chainlink/contracts/src/v0.8/interfaces/AggregatorV3Interface.sol"
      ],
      "versionPragmas": [
        "^0.8.19"
      ],
      "artifacts": [
        "CivicXChainGovernance"
      ]
    },
    "/Users/kimberleycheung/Desktop/CiviXchain8/civicxchain-platform/contracts/node_modules/@openzeppelin/contracts/access/Ownable.sol": {
      "lastModificationDate": 1755096494945,
      "contentHash": "5a20b2cad87ddb61c7a3a6af21289e28",
      "sourceName": "@openzeppelin/contracts/access/Ownable.sol",
      "solcConfig": {
        "version": "0.8.28",
        "settings": {
          "optimizer": {
            "enabled": true,
            "runs": 200
          },
          "viaIR": true,
          "evmVersion": "paris",
          "outputSelection": {
            "*": {
              "*": [
                "abi",
                "evm.bytecode",
                "evm.deployedBytecode",
                "evm.methodIdentifiers",
                "metadata"
              ],
              "": [
                "ast"
              ]
            }
          }
        }
      },
      "imports": [
        "../utils/Context.sol"
      ],
      "versionPragmas": [
        "^0.8.0"
      ],
      "artifacts": [
        "Ownable"
      ]
    },
    "/Users/kimberleycheung/Desktop/CiviXchain8/civicxchain-platform/contracts/node_modules/@openzeppelin/contracts/security/ReentrancyGuard.sol": {
      "lastModificationDate": 1755096494947,
      "contentHash": "1535f8c0c68463f8c1b5239f7584e71f",
      "sourceName": "@openzeppelin/contracts/security/ReentrancyGuard.sol",
      "solcConfig": {
        "version": "0.8.28",
        "settings": {
          "optimizer": {
            "enabled": true,
            "runs": 200
          },
          "viaIR": true,
          "evmVersion": "paris",
          "outputSelection": {
            "*": {
              "*": [
                "abi",
                "evm.bytecode",
                "evm.deployedBytecode",
                "evm.methodIdentifiers",
                "metadata"
              ],
              "": [
                "ast"
              ]
            }
          }
        }
      },
      "imports": [],
      "versionPragmas": [
        "^0.8.0"
      ],
      "artifacts": [
        "ReentrancyGuard"
      ]
    },
    "/Users/kimberleycheung/Desktop/CiviXchain8/civicxchain-platform/contracts/node_modules/@openzeppelin/contracts/token/ERC20/ERC20.sol": {
      "lastModificationDate": 1755096494928,
      "contentHash": "3ae5166c6827a9cf1a7a462d1632b464",
      "sourceName": "@openzeppelin/contracts/token/ERC20/ERC20.sol",
      "solcConfig": {
        "version": "0.8.28",
        "settings": {
          "optimizer": {
            "enabled": true,
            "runs": 200
          },
          "viaIR": true,
          "evmVersion": "paris",
          "outputSelection": {
            "*": {
              "*": [
                "abi",
                "evm.bytecode",
                "evm.deployedBytecode",
                "evm.methodIdentifiers",
                "metadata"
              ],
              "": [
                "ast"
              ]
            }
          }
        }
      },
      "imports": [
        "./IERC20.sol",
        "./extensions/IERC20Metadata.sol",
        "../../utils/Context.sol"
      ],
      "versionPragmas": [
        "^0.8.0"
      ],
      "artifacts": [
        "ERC20"
      ]
    },
    "/Users/kimberleycheung/Desktop/CiviXchain8/civicxchain-platform/contracts/node_modules/@openzeppelin/contracts/utils/Context.sol": {
      "lastModificationDate": 1755096495021,
      "contentHash": "f07feb4a44b1a4872370da5aa70e8e46",
      "sourceName": "@openzeppelin/contracts/utils/Context.sol",
      "solcConfig": {
        "version": "0.8.28",
        "settings": {
          "optimizer": {
            "enabled": true,
            "runs": 200
          },
          "viaIR": true,
          "evmVersion": "paris",
          "outputSelection": {
            "*": {
              "*": [
                "abi",
                "evm.bytecode",
                "evm.deployedBytecode",
                "evm.methodIdentifiers",
                "metadata"
              ],
              "": [
                "ast"
              ]
            }
          }
        }
      },
      "imports": [],
      "versionPragmas": [
        "^0.8.0"
      ],
      "artifacts": [
        "Context"
      ]
    },
    "/Users/kimberleycheung/Desktop/CiviXchain8/civicxchain-platform/contracts/node_modules/@openzeppelin/contracts/token/ERC20/IERC20.sol": {
      "lastModificationDate": 1755096494928,
      "contentHash": "df36f7051335cd1e748b1b6463b7fdd3",
      "sourceName": "@openzeppelin/contracts/token/ERC20/IERC20.sol",
      "solcConfig": {
        "version": "0.8.28",
        "settings": {
          "optimizer": {
            "enabled": true,
            "runs": 200
          },
          "viaIR": true,
          "evmVersion": "paris",
          "outputSelection": {
            "*": {
              "*": [
                "abi",
                "evm.bytecode",
                "evm.deployedBytecode",
                "evm.methodIdentifiers",
                "metadata"
              ],
              "": [
                "ast"
              ]
            }
          }
        }
      },
      "imports": [],
      "versionPragmas": [
        "^0.8.0"
      ],
      "artifacts": [
        "IERC20"
      ]
    },
    "/Users/kimberleycheung/Desktop/CiviXchain8/civicxchain-platform/contracts/node_modules/@openzeppelin/contracts/token/ERC20/extensions/IERC20Metadata.sol": {
      "lastModificationDate": 1755096494930,
      "contentHash": "909ab67fc5c25033fe6cd364f8c056f9",
      "sourceName": "@openzeppelin/contracts/token/ERC20/extensions/IERC20Metadata.sol",
      "solcConfig": {
        "version": "0.8.28",
        "settings": {
          "optimizer": {
            "enabled": true,
            "runs": 200
          },
          "viaIR": true,
          "evmVersion": "paris",
          "outputSelection": {
            "*": {
              "*": [
                "abi",
                "evm.bytecode",
                "evm.deployedBytecode",
                "evm.methodIdentifiers",
                "metadata"
              ],
              "": [
                "ast"
              ]
            }
          }
        }
      },
      "imports": [
        "../IERC20.sol"
      ],
      "versionPragmas": [
        "^0.8.0"
      ],
      "artifacts": [
        "IERC20Metadata"
      ]
    }
  }
}
